Metadata-Version: 2.1
Name: asynker
Version: 0.6
Summary: Coroutine scheduler for Python 3.5's await syntax
Home-page: https://github.com/enkore/asynker
Author: Marian Beermann
Author-email: asynker@enkore.de
License: MIT
Platform: UNKNOWN
Classifier: Development Status :: 3 - Alpha
Classifier: Programming Language :: Python :: 3
Classifier: Programming Language :: Python :: 3.6
Provides-Extra: test
